{"data_as_of":"2026-05-14","qqqm_pct":70.9,"qqqm_warning":false,"risk_total":null,"rows":[{"amount":null,"avg_cost":null,"deviation_pct":10.9,"effective_pct":70.9,"gain_pct":18.63,"is_cash":false,"pct":48.5,"price":296.37,"shares":null,"symbol":"QQQM","target_pct":60},{"amount":null,"avg_cost":null,"deviation_pct":0,"effective_pct":null,"gain_pct":0.47,"is_cash":true,"pct":31.6,"price":116.69,"shares":null,"symbol":"BOXX","target_pct":0},{"amount":null,"avg_cost":null,"deviation_pct":-5.6,"effective_pct":19.4,"gain_pct":-2.42,"is_cash":false,"pct":13.3,"price":484.06,"shares":null,"symbol":"BRK.B","target_pct":25},{"amount":null,"avg_cost":null,"deviation_pct":-5.3,"effective_pct":9.7,"gain_pct":-5.52,"is_cash":false,"pct":6.6,"price":87.54,"shares":null,"symbol":"IAU","target_pct":15}],"total_value":null}